{"stat.craftItem.minecraft.stone_slab":513,"stat.flyOneCm":374441,"stat.walkOneCm":52683,"stat.jump":86,"stat.playOneMinute":44941,"achievement.openInventory":13,"stat.craftItem.minecraft.brick_block":44,"stat.craftItem.minecraft.stone":6,"stat.leaveGame":1,"stat.sneakTime":111,"stat.craftItem.minecraft.stained_glass":48,"stat.crouchOneCm":7,"stat.timeSinceDeath":44941,"stat.craftItem.minecraft.stone_brick_stairs":11,"stat.sprintOneCm":144,"achievement.exploreAllBiomes":{"value":0,"progress":["Forest","River","Plains"]},"stat.craftItem.minecraft.sandstone":105}